winwin/__init__.py
winwin/dingtalk.py
winwin/env.py
winwin/oss.py
winwin/tos.py
winwin/ark/__init__.py
winwin/ark/batch_infer.py
winwin/ark/utils.py
winwin/managers/__init__.py
winwin/managers/nebula.py
winwin/managers/odps.py
winwin/managers/oss.py
winwin/managers/resource.py
winwin/prefect/__init__.py
winwin/prefect/aliyun.py
winwin/prefect/odps.py
winwin/prefect/ssh.py
winwin/utils/__init__.py
winwin/utils/device_util.py
winwin/utils/file_util.py
winwin/utils/func_util.py
winwin/utils/list_util.py
winwin/utils/os_util.py
winwin/utils/pd_util.py
winwin/utils/pool_util.py
winwin/utils/str_util.py
winwin/utils/support.py
winwin/utils/time_util.py
winwin/utils/barcode/GtinCountryCode.py
winwin/utils/barcode/__init__.py
winwin/utils/barcode/iso3166.csv
winwin-0.0.61.dist-info/METADATA
winwin-0.0.61.dist-info/WHEEL
winwin-0.0.61.dist-info/entry_points.txt
winwin-0.0.61.dist-info/RECORD
