Metadata-Version: 2.4
Name: winwin
Version: 0.0.61
Summary: Add your description here
Author-email: 赵斌 <zhaobin@brandct.com>
Classifier: License :: OSI Approved :: MIT License
Classifier: Operating System :: OS Independent
Classifier: Programming Language :: Python :: 3
Requires-Python: >=3.9
Requires-Dist: backoff>=2.2.1
Requires-Dist: pytest-asyncio>=0.26.0
Requires-Dist: python-dotenv>=1.0.1
Requires-Dist: pyyaml>=6.0.2
Requires-Dist: volcengine-python-sdk[ark]>=2.0.1
Provides-Extra: oss
Requires-Dist: ossfs>=2023.12.0; extra == 'oss'
Provides-Extra: prefect
Requires-Dist: fabric>=3.2.2; extra == 'prefect'
Requires-Dist: ossfs>=2023.12.0; extra == 'prefect'
Requires-Dist: prefect-client>=3.2.7; extra == 'prefect'
Requires-Dist: pyodps>=0.12.2; extra == 'prefect'
